__init__.py
data_gempa/__init__.py
Indoearth-0.0.1.dist-info/LICENSE
Indoearth-0.0.1.dist-info/METADATA
Indoearth-0.0.1.dist-info/WHEEL
Indoearth-0.0.1.dist-info/top_level.txt
Indoearth-0.0.1.dist-info/RECORD
