Metadata-Version: 2.1
Name: Indoearth
Version: 0.0.1
Summary: a package that can retrieve the latest earthquake data taken from the website of the BMKG (Meteorological, Climatological, and Geophysical Agency).
Author-email: Danang <danangfirmino26@gmail.com>
Project-URL: Homepage, https://github.com/danangfir/Indonesia-latest-earthquake
Project-URL: Bug Tracker, https://github.com/danangfir/Indonesia-latest-earthquake
Classifier: Programming Language :: Python :: 3
Classifier: License :: OSI Approved :: MIT License
Classifier: Operating System :: OS Independent
Requires-Python: >=3.7
License-File: LICENSE
